njord/__init__.py
njord/_templates.py
njord/_utils.py
njord/client.py
njord-0.0.2.dist-info/LICENSE
njord-0.0.2.dist-info/METADATA
njord-0.0.2.dist-info/WHEEL
njord-0.0.2.dist-info/top_level.txt
njord-0.0.2.dist-info/RECORD
