Metadata-Version: 2.1
Name: njord
Version: 0.0.2
Summary: A Python package for programmatically controlling NordVPN.
Home-page: https://github.com/admjs/njord
Author: admjs
Author-email: ajs@sent.com
Project-URL: Bug Tracker, https://github.com/admjs/njord/-/issues
Project-URL: repository, https://github.com/admjs/njord
Classifier: Development Status :: 2 - Pre-Alpha
Classifier: Intended Audience :: Developers
Classifier: License :: OSI Approved :: MIT License
Classifier: Operating System :: POSIX :: Linux
Classifier: Operating System :: MacOS :: MacOS X
Classifier: Environment :: MacOS X
Classifier: Programming Language :: Python :: 3 :: Only
Classifier: Programming Language :: Unix Shell
Classifier: Natural Language :: English
Classifier: Topic :: Internet :: WWW/HTTP
Classifier: Topic :: Utilities
Requires-Python: >=3.6
License-File: LICENSE
Requires-Dist: requests
Requires-Dist: python-dotenv
Requires-Dist: psutil
